zhang_suen_thinning.cpython-39-x86_64-linux-gnu.so
torch_thinning/__init__.py
torch_thinning/zhang_suen_thinning_kernel.cu
torch_thinning-1.0.0.dist-info/LICENSE
torch_thinning-1.0.0.dist-info/METADATA
torch_thinning-1.0.0.dist-info/WHEEL
torch_thinning-1.0.0.dist-info/top_level.txt
torch_thinning-1.0.0.dist-info/RECORD
